{
    "updated_cases": [
        {
            "id": 1537458,
            "title": "Verify the sqlite file genaration ,when we edit  the category  based bypass policy",
            "section_id": 105681,
            "template_id": 1,
            "type_id": 6,
            "priority_id": 2,
            "milestone_id": null,
            "refs": null,
            "created_by": 350,
            "created_on": 1682328799,
            "updated_by": 729,
            "updated_on": 1736856402,
            "estimate": null,
            "estimate_forecast": null,
            "suite_id": 921,
            "display_order": 11,
            "is_deleted": 0,
            "case_assignedto_id": null,
            "custom_automation_type": 0,
            "custom_automatable": 1,
            "custom_automated": 1,
            "custom_deprecatedtestcase": null,
            "custom_ui_case": 1,
            "custom_automation_id": null,
            "custom_hack_functional_sub_categories": 1,
            "custom_hack_test_categories": 3,
            "custom_hack_jira_escalated": null,
            "custom_appliance_support": null,
            "custom_sub_component": 48,
            "custom_testrail_bdd_scenario": null,
            "custom_summary": "edit the category based bypass policy",
            "custom_preconds": null,
            "custom_steps": "Edit the Category based Bypass Policy in UI\nCheck the end to end flow",
            "custom_expected": "Policy flow should work as expected here",
            "custom_steps_separated": null,
            "custom_mission": null,
            "custom_goals": null,
            "comments": [],
            "custom_keyword": [],
            "custom_stack_label": []
        },
        {
            "id": 1537459,
            "title": "Verify the sqlite file genaration ,when we delete the category  based bypass  policy",
            "section_id": 105681,
            "template_id": 1,
            "type_id": 6,
            "priority_id": 2,
            "milestone_id": null,
            "refs": null,
            "created_by": 350,
            "created_on": 1682328799,
            "updated_by": 729,
            "updated_on": 1736856402,
            "estimate": null,
            "estimate_forecast": null,
            "suite_id": 921,
            "display_order": 12,
            "is_deleted": 0,
            "case_assignedto_id": null,
            "custom_automation_type": 0,
            "custom_automatable": 1,
            "custom_automated": 1,
            "custom_deprecatedtestcase": null,
            "custom_ui_case": 1,
            "custom_automation_id": null,
            "custom_hack_functional_sub_categories": 1,
            "custom_hack_test_categories": 3,
            "custom_hack_jira_escalated": null,
            "custom_appliance_support": null,
            "custom_sub_component": 48,
            "custom_testrail_bdd_scenario": null,
            "custom_summary": "delete the category based bypass policy",
            "custom_preconds": null,
            "custom_steps": "Delete the Category based Bypass Policy in UI\nCheck the end to end flow",
            "custom_expected": "Policy flow should work as expected here",
            "custom_steps_separated": null,
            "custom_mission": null,
            "custom_goals": null,
            "comments": [],
            "custom_keyword": [],
            "custom_stack_label": []
        },
        {
            "id": 1537460,
            "title": "Verify the end to end flow Constraint Profile based policy",
            "section_id": 105681,
            "template_id": 1,
            "type_id": 6,
            "priority_id": 2,
            "milestone_id": null,
            "refs": null,
            "created_by": 350,
            "created_on": 1682328799,
            "updated_by": 729,
            "updated_on": 1736856402,
            "estimate": null,
            "estimate_forecast": null,
            "suite_id": 921,
            "display_order": 13,
            "is_deleted": 0,
            "case_assignedto_id": null,
            "custom_automation_type": 0,
            "custom_automatable": 1,
            "custom_automated": 1,
            "custom_deprecatedtestcase": null,
            "custom_ui_case": 1,
            "custom_automation_id": null,
            "custom_hack_functional_sub_categories": 1,
            "custom_hack_test_categories": 3,
            "custom_hack_jira_escalated": null,
            "custom_appliance_support": null,
            "custom_sub_component": 48,
            "custom_testrail_bdd_scenario": null,
            "custom_summary": "Check the constraint profile based policy end to end flow",
            "custom_preconds": null,
            "custom_steps": "Create the Constraint Profile based policy in UI\nValidate the end to end flow",
            "custom_expected": "Constraint profile policy should work as expected",
            "custom_steps_separated": null,
            "custom_mission": null,
            "custom_goals": null,
            "comments": [],
            "custom_keyword": [],
            "custom_stack_label": []
        },
        {
            "id": 1537461,
            "title": "Verify the constraint_profile.json,after adding new constraint profile",
            "section_id": 105681,
            "template_id": 1,
            "type_id": 6,
            "priority_id": 2,
            "milestone_id": null,
            "refs": null,
            "created_by": 350,
            "created_on": 1682328799,
            "updated_by": 729,
            "updated_on": 1736856402,
            "estimate": null,
            "estimate_forecast": null,
            "suite_id": 921,
            "display_order": 14,
            "is_deleted": 0,
            "case_assignedto_id": null,
            "custom_automation_type": 0,
            "custom_automatable": 1,
            "custom_automated": 1,
            "custom_deprecatedtestcase": null,
            "custom_ui_case": 1,
            "custom_automation_id": null,
            "custom_hack_functional_sub_categories": 1,
            "custom_hack_test_categories": 3,
            "custom_hack_jira_escalated": null,
            "custom_appliance_support": null,
            "custom_sub_component": 48,
            "custom_testrail_bdd_scenario": null,
            "custom_summary": "Check the constraint profile based policy end to end flow",
            "custom_preconds": null,
            "custom_steps": "Create the Constraint Profile based policy in UI\nValidate the end to end flow",
            "custom_expected": "Constraint profile policy should work as expected",
            "custom_steps_separated": null,
            "custom_mission": null,
            "custom_goals": null,
            "comments": [],
            "custom_keyword": [],
            "custom_stack_label": []
        },
        {
            "id": 1537462,
            "title": "Verify the constraint_profile.json,after deleting constraint profile",
            "section_id": 105681,
            "template_id": 1,
            "type_id": 6,
            "priority_id": 2,
            "milestone_id": null,
            "refs": null,
            "created_by": 350,
            "created_on": 1682328799,
            "updated_by": 729,
            "updated_on": 1736856402,
            "estimate": null,
            "estimate_forecast": null,
            "suite_id": 921,
            "display_order": 15,
            "is_deleted": 0,
            "case_assignedto_id": null,
            "custom_automation_type": 0,
            "custom_automatable": 1,
            "custom_automated": 1,
            "custom_deprecatedtestcase": null,
            "custom_ui_case": 1,
            "custom_automation_id": null,
            "custom_hack_functional_sub_categories": 1,
            "custom_hack_test_categories": 3,
            "custom_hack_jira_escalated": null,
            "custom_appliance_support": null,
            "custom_sub_component": 48,
            "custom_testrail_bdd_scenario": null,
            "custom_summary": "Check the constraint profile based policy end to end flow",
            "custom_preconds": null,
            "custom_steps": "Delete the Constraint Profile based policy in UI\nValidate the end to end flow",
            "custom_expected": "Constraint profile policy should work as expected",
            "custom_steps_separated": null,
            "custom_mission": null,
            "custom_goals": null,
            "comments": [],
            "custom_keyword": [],
            "custom_stack_label": []
        },
        {
            "id": 1537463,
            "title": "Verify the constraint_profile.json,after editing constraint profile",
            "section_id": 105681,
            "template_id": 1,
            "type_id": 6,
            "priority_id": 2,
            "milestone_id": null,
            "refs": null,
            "created_by": 350,
            "created_on": 1682328799,
            "updated_by": 729,
            "updated_on": 1736856402,
            "estimate": null,
            "estimate_forecast": null,
            "suite_id": 921,
            "display_order": 16,
            "is_deleted": 0,
            "case_assignedto_id": null,
            "custom_automation_type": 0,
            "custom_automatable": 1,
            "custom_automated": 1,
            "custom_deprecatedtestcase": null,
            "custom_ui_case": 1,
            "custom_automation_id": null,
            "custom_hack_functional_sub_categories": 1,
            "custom_hack_test_categories": 3,
            "custom_hack_jira_escalated": null,
            "custom_appliance_support": null,
            "custom_sub_component": 48,
            "custom_testrail_bdd_scenario": null,
            "custom_summary": "Check the constraint profile based policy end to end flow",
            "custom_preconds": null,
            "custom_steps": "Edit the Constraint Profile based policy in UI\nValidate the end to end flow",
            "custom_expected": "Constraint profile policy should work as expected",
            "custom_steps_separated": null,
            "custom_mission": null,
            "custom_goals": null,
            "comments": [],
            "custom_keyword": [],
            "custom_stack_label": []
        },
        {
            "id": 1537464,
            "title": "Verify the end to end behaviour for User group/OU based policies",
            "section_id": 105681,
            "template_id": 1,
            "type_id": 6,
            "priority_id": 2,
            "milestone_id": null,
            "refs": null,
            "created_by": 350,
            "created_on": 1682328799,
            "updated_by": 729,
            "updated_on": 1736856402,
            "estimate": null,
            "estimate_forecast": null,
            "suite_id": 921,
            "display_order": 17,
            "is_deleted": 0,
            "case_assignedto_id": null,
            "custom_automation_type": 0,
            "custom_automatable": 1,
            "custom_automated": 1,
            "custom_deprecatedtestcase": null,
            "custom_ui_case": 1,
            "custom_automation_id": null,
            "custom_hack_functional_sub_categories": 1,
            "custom_hack_test_categories": 3,
            "custom_hack_jira_escalated": null,
            "custom_appliance_support": null,
            "custom_sub_component": 48,
            "custom_testrail_bdd_scenario": null,
            "custom_summary": null,
            "custom_preconds": null,
            "custom_steps": null,
            "custom_expected": null,
            "custom_steps_separated": null,
            "custom_mission": null,
            "custom_goals": null,
            "comments": [],
            "custom_keyword": [],
            "custom_stack_label": []
        },
        {
            "id": 1537465,
            "title": "Verify custom template html proxy sync",
            "section_id": 105681,
            "template_id": 1,
            "type_id": 6,
            "priority_id": 2,
            "milestone_id": null,
            "refs": null,
            "created_by": 350,
            "created_on": 1682328799,
            "updated_by": 729,
            "updated_on": 1736856402,
            "estimate": null,
            "estimate_forecast": null,
            "suite_id": 921,
            "display_order": 18,
            "is_deleted": 0,
            "case_assignedto_id": null,
            "custom_automation_type": 0,
            "custom_automatable": 1,
            "custom_automated": 1,
            "custom_deprecatedtestcase": null,
            "custom_ui_case": 1,
            "custom_automation_id": null,
            "custom_hack_functional_sub_categories": 1,
            "custom_hack_test_categories": 3,
            "custom_hack_jira_escalated": null,
            "custom_appliance_support": null,
            "custom_sub_component": 48,
            "custom_testrail_bdd_scenario": null,
            "custom_summary": null,
            "custom_preconds": null,
            "custom_steps": null,
            "custom_expected": null,
            "custom_steps_separated": null,
            "custom_mission": null,
            "custom_goals": null,
            "comments": [],
            "custom_keyword": [],
            "custom_stack_label": [
                4
            ]
        },
        {
            "id": 1537536,
            "title": "Verify that the migration doesn't introduce any regression/negative effects with respect to policy 3.0",
            "section_id": 105682,
            "template_id": 1,
            "type_id": 6,
            "priority_id": 2,
            "milestone_id": null,
            "refs": null,
            "created_by": 350,
            "created_on": 1682328800,
            "updated_by": 729,
            "updated_on": 1736856402,
            "estimate": null,
            "estimate_forecast": null,
            "suite_id": 921,
            "display_order": 1,
            "is_deleted": 0,
            "case_assignedto_id": null,
            "custom_automation_type": 0,
            "custom_automatable": 1,
            "custom_automated": 1,
            "custom_deprecatedtestcase": null,
            "custom_ui_case": 1,
            "custom_automation_id": null,
            "custom_hack_functional_sub_categories": 1,
            "custom_hack_test_categories": 3,
            "custom_hack_jira_escalated": null,
            "custom_appliance_support": null,
            "custom_sub_component": 48,
            "custom_testrail_bdd_scenario": null,
            "custom_summary": null,
            "custom_preconds": null,
            "custom_steps": null,
            "custom_expected": null,
            "custom_steps_separated": null,
            "custom_mission": null,
            "custom_goals": null,
            "comments": [],
            "custom_keyword": [],
            "custom_stack_label": []
        },
        {
            "id": 1537537,
            "title": "Verify that the migration doesn't introduce any regression/negative effects with respect to Risk based policies",
            "section_id": 105682,
            "template_id": 1,
            "type_id": 6,
            "priority_id": 2,
            "milestone_id": null,
            "refs": null,
            "created_by": 350,
            "created_on": 1682328800,
            "updated_by": 729,
            "updated_on": 1736856402,
            "estimate": null,
            "estimate_forecast": null,
            "suite_id": 921,
            "display_order": 2,
            "is_deleted": 0,
            "case_assignedto_id": null,
            "custom_automation_type": 0,
            "custom_automatable": 1,
            "custom_automated": 1,
            "custom_deprecatedtestcase": null,
            "custom_ui_case": 1,
            "custom_automation_id": null,
            "custom_hack_functional_sub_categories": 1,
            "custom_hack_test_categories": 3,
            "custom_hack_jira_escalated": null,
            "custom_appliance_support": null,
            "custom_sub_component": 48,
            "custom_testrail_bdd_scenario": null,
            "custom_summary": null,
            "custom_preconds": null,
            "custom_steps": null,
            "custom_expected": null,
            "custom_steps_separated": null,
            "custom_mission": null,
            "custom_goals": null,
            "comments": [],
            "custom_keyword": [],
            "custom_stack_label": [
                4
            ]
        }
    ]
}