{
    "updated_cases": [
        {
            "id": 1806459,
            "title": "Verify vpop IP is used and DEIP policy is matched",
            "section_id": 125298,
            "template_id": 1,
            "type_id": 6,
            "priority_id": 2,
            "milestone_id": null,
            "refs": "ENG-400726",
            "created_by": 398,
            "created_on": 1709679676,
            "updated_by": 729,
            "updated_on": 1736856007,
            "estimate": null,
            "estimate_forecast": null,
            "suite_id": 921,
            "display_order": 5,
            "is_deleted": 0,
            "case_assignedto_id": null,
            "custom_automation_type": 0,
            "custom_automatable": 1,
            "custom_automated": 1,
            "custom_deprecatedtestcase": false,
            "custom_ui_case": 1,
            "custom_automation_id": null,
            "custom_hack_functional_sub_categories": 1,
            "custom_hack_test_categories": 3,
            "custom_hack_jira_escalated": false,
            "custom_appliance_support": 2,
            "custom_sub_component": 48,
            "custom_testrail_bdd_scenario": null,
            "custom_summary": null,
            "custom_preconds": null,
            "custom_steps": "- Configure 'tenant_footprint.json' with multple footprint\n- Create DEIP policy with \"egress_ip_type\": shared\n- Route traffic and check vpop ip is used\n- Verify the DEIP policy match using logs",
            "custom_expected": "- DEIP policy is matched\n- VPOP IP is used for traffic\n- Review appmodule 3 logs to see so_mark picked \n- Review policy 1 logs, to see EgressIP policy being picked indicated by ns_policy_apply_egress_ip_policy()",
            "custom_steps_separated": null,
            "custom_mission": null,
            "custom_goals": null,
            "comments": [],
            "custom_keyword": [],
            "custom_stack_label": []
        },
        {
            "id": 1806460,
            "title": "Verify DEIP policy is matched but DEIP is not used since footprint_id is not present in json",
            "section_id": 125298,
            "template_id": 1,
            "type_id": 6,
            "priority_id": 2,
            "milestone_id": null,
            "refs": "ENG-400726",
            "created_by": 398,
            "created_on": 1709679676,
            "updated_by": 729,
            "updated_on": 1736856007,
            "estimate": null,
            "estimate_forecast": null,
            "suite_id": 921,
            "display_order": 6,
            "is_deleted": 0,
            "case_assignedto_id": null,
            "custom_automation_type": 0,
            "custom_automatable": 1,
            "custom_automated": 1,
            "custom_deprecatedtestcase": false,
            "custom_ui_case": 1,
            "custom_automation_id": null,
            "custom_hack_functional_sub_categories": 1,
            "custom_hack_test_categories": 3,
            "custom_hack_jira_escalated": false,
            "custom_appliance_support": 2,
            "custom_sub_component": 48,
            "custom_testrail_bdd_scenario": null,
            "custom_summary": null,
            "custom_preconds": null,
            "custom_steps": "- Create DEIP with footprint id not present in tenant_footprint.json\n- Send traffic to match the policy\n- check that DEIP is not used since footprint id is not present\n- VPOP IP or regular ip is used based on vpop enablement",
            "custom_expected": "DEIP should not be used\nVPOP or DE IP is used based on the vpop status",
            "custom_steps_separated": null,
            "custom_mission": null,
            "custom_goals": null,
            "comments": [],
            "custom_keyword": [],
            "custom_stack_label": []
        },
        {
            "id": 1806461,
            "title": "Verify invalid footprint_id in DEIP policy",
            "section_id": 125298,
            "template_id": 1,
            "type_id": 6,
            "priority_id": 2,
            "milestone_id": null,
            "refs": "ENG-400726",
            "created_by": 398,
            "created_on": 1709679676,
            "updated_by": 729,
            "updated_on": 1736856007,
            "estimate": null,
            "estimate_forecast": null,
            "suite_id": 921,
            "display_order": 7,
            "is_deleted": 0,
            "case_assignedto_id": null,
            "custom_automation_type": 0,
            "custom_automatable": 1,
            "custom_automated": 1,
            "custom_deprecatedtestcase": false,
            "custom_ui_case": 1,
            "custom_automation_id": null,
            "custom_hack_functional_sub_categories": 1,
            "custom_hack_test_categories": 3,
            "custom_hack_jira_escalated": false,
            "custom_appliance_support": 2,
            "custom_sub_component": 48,
            "custom_testrail_bdd_scenario": null,
            "custom_summary": null,
            "custom_preconds": null,
            "custom_steps": "- Create DEIP with invalid footprint id with string\n- Verify policy creation shouldnot through error",
            "custom_expected": "dpmgmtsvc should reject invalid configuration",
            "custom_steps_separated": null,
            "custom_mission": null,
            "custom_goals": null,
            "comments": [],
            "custom_keyword": [],
            "custom_stack_label": []
        },
        {
            "id": 1806462,
            "title": "Verify invalid egress_ip_type in DEIP policy",
            "section_id": 125298,
            "template_id": 1,
            "type_id": 6,
            "priority_id": 2,
            "milestone_id": null,
            "refs": "ENG-400726",
            "created_by": 398,
            "created_on": 1709679676,
            "updated_by": 729,
            "updated_on": 1736856007,
            "estimate": null,
            "estimate_forecast": null,
            "suite_id": 921,
            "display_order": 8,
            "is_deleted": 0,
            "case_assignedto_id": null,
            "custom_automation_type": 0,
            "custom_automatable": 1,
            "custom_automated": 1,
            "custom_deprecatedtestcase": false,
            "custom_ui_case": 1,
            "custom_automation_id": null,
            "custom_hack_functional_sub_categories": 1,
            "custom_hack_test_categories": 3,
            "custom_hack_jira_escalated": false,
            "custom_appliance_support": 2,
            "custom_sub_component": 48,
            "custom_testrail_bdd_scenario": null,
            "custom_summary": null,
            "custom_preconds": null,
            "custom_steps": "- Create DEIP policy with invalid egress_ip_type (except: dedicated/shared)\n- Check policy creation should fail",
            "custom_expected": "dpmgmtsvc should reject invalid configuration",
            "custom_steps_separated": null,
            "custom_mission": null,
            "custom_goals": null,
            "comments": [],
            "custom_keyword": [],
            "custom_stack_label": []
        },
        {
            "id": 1806463,
            "title": "Verify DEIP policy match for one source AND destination with dedicated and shared egress type",
            "section_id": 125298,
            "template_id": 1,
            "type_id": 6,
            "priority_id": 2,
            "milestone_id": null,
            "refs": "ENG-400726",
            "created_by": 398,
            "created_on": 1709679676,
            "updated_by": 729,
            "updated_on": 1736856007,
            "estimate": null,
            "estimate_forecast": null,
            "suite_id": 921,
            "display_order": 9,
            "is_deleted": 0,
            "case_assignedto_id": null,
            "custom_automation_type": 0,
            "custom_automatable": 1,
            "custom_automated": 1,
            "custom_deprecatedtestcase": null,
            "custom_ui_case": 1,
            "custom_automation_id": null,
            "custom_hack_functional_sub_categories": 1,
            "custom_hack_test_categories": 3,
            "custom_hack_jira_escalated": null,
            "custom_appliance_support": 2,
            "custom_sub_component": 48,
            "custom_testrail_bdd_scenario": null,
            "custom_summary": null,
            "custom_preconds": null,
            "custom_steps": "- Create DEIP policy with one Source AND one Destination\r\nSrc: User: bkodirangaiah@netskope.com\r\nDst: Domain==ifconfig.me\r\negress_ip_profile: \r\n          egress_ip_type:Dedicated/Shared\r\n          footprint : 12345\r\n- Send traffic to match the policy\r\n- Check that the policy is matched, and ensure that the corresponding IPs are used and that logs are generated.",
            "custom_expected": "- DEIP policy is matched\r\n- DE/VPOP IP is used for traffic\r\n- Review appmodule 3 logs to see so_mark picked \r\n- Review policy 1 logs, to see EgressIP policy being picked indicated by ns_policy_apply_egress_ip_policy()",
            "custom_steps_separated": null,
            "custom_mission": null,
            "custom_goals": null,
            "comments": [],
            "custom_keyword": [],
            "custom_stack_label": []
        },
        {
            "id": 1806464,
            "title": "Verify DEIP policy match with exclusion in Source and Destination field with egress_ip_type shared",
            "section_id": 125298,
            "template_id": 1,
            "type_id": 6,
            "priority_id": 2,
            "milestone_id": null,
            "refs": "ENG-400726",
            "created_by": 398,
            "created_on": 1709679676,
            "updated_by": 729,
            "updated_on": 1736856007,
            "estimate": null,
            "estimate_forecast": null,
            "suite_id": 921,
            "display_order": 10,
            "is_deleted": 0,
            "case_assignedto_id": null,
            "custom_automation_type": 0,
            "custom_automatable": 1,
            "custom_automated": 1,
            "custom_deprecatedtestcase": false,
            "custom_ui_case": 1,
            "custom_automation_id": null,
            "custom_hack_functional_sub_categories": 1,
            "custom_hack_test_categories": 3,
            "custom_hack_jira_escalated": false,
            "custom_appliance_support": 2,
            "custom_sub_component": 48,
            "custom_testrail_bdd_scenario": null,
            "custom_summary": null,
            "custom_preconds": null,
            "custom_steps": "- Create DEIP policy with exclusion in Source AND Destination\nSrc: User: exclude: bk-test01@netskope.com\n       Source IP User: exclude: 2.2.2.2\nDst: App==Box\n       Des IP: exclude: 10.10.10.1\negress_ip_profile: \n          egress_ip_type:Dedicated/Shared\n          footprint : 12345\n- Send traffic to match the policy\n- Check that the policy is matched, and ensure that the corresponding IPs are used and that logs are generated.",
            "custom_expected": "- DEIP policy is matched\n- DE/VPOP IP is used for traffic\n- Review appmodule 3 logs to see so_mark picked \n- Review policy 1 logs, to see EgressIP policy being picked indicated by ns_policy_apply_egress_ip_policy()",
            "custom_steps_separated": null,
            "custom_mission": null,
            "custom_goals": null,
            "comments": [],
            "custom_keyword": [],
            "custom_stack_label": []
        },
        {
            "id": 1806465,
            "title": "Verify DEIP policy match for multiple source AND destination with dedicated and shared egress type",
            "section_id": 125298,
            "template_id": 1,
            "type_id": 6,
            "priority_id": 2,
            "milestone_id": null,
            "refs": "ENG-400726",
            "created_by": 398,
            "created_on": 1709679676,
            "updated_by": 729,
            "updated_on": 1736856007,
            "estimate": null,
            "estimate_forecast": null,
            "suite_id": 921,
            "display_order": 11,
            "is_deleted": 0,
            "case_assignedto_id": null,
            "custom_automation_type": 0,
            "custom_automatable": 1,
            "custom_automated": 1,
            "custom_deprecatedtestcase": false,
            "custom_ui_case": 1,
            "custom_automation_id": null,
            "custom_hack_functional_sub_categories": 1,
            "custom_hack_test_categories": 3,
            "custom_hack_jira_escalated": false,
            "custom_appliance_support": 2,
            "custom_sub_component": 48,
            "custom_testrail_bdd_scenario": null,
            "custom_summary": null,
            "custom_preconds": null,
            "custom_steps": "- Create DEIP policy with Source AND Destination\nSrc: User: bk-test01@netskope.com\n        Src IP Egress: 1.1.1.1\nDst: App==Box\n        Cat==Cloud\n        Domain==*.box.com\n        Dest IP==10.1.1.1 (DoesNotMatch)\negress_ip_profile: \n          egress_ip_type:Dedicated/Shared\n          footprint : 12345\n- Send traffic to match the policy\n- Check that the policy is matched, and ensure that the corresponding IPs are used and that logs are generated.",
            "custom_expected": "- DEIP policy is matched\n- DE/VPOP IP is used for traffic\n- Review appmodule 3 logs to see so_mark picked \n- Review policy 1 logs, to see EgressIP policy being picked indicated by ns_policy_apply_egress_ip_policy()",
            "custom_steps_separated": null,
            "custom_mission": null,
            "custom_goals": null,
            "comments": [],
            "custom_keyword": [],
            "custom_stack_label": []
        },
        {
            "id": 1806466,
            "title": "Verify sending traffic without matching the policy shouldn't see dedicated/shared egress IP",
            "section_id": 125298,
            "template_id": 1,
            "type_id": 6,
            "priority_id": 2,
            "milestone_id": null,
            "refs": "ENG-400726",
            "created_by": 398,
            "created_on": 1709679676,
            "updated_by": 729,
            "updated_on": 1736856007,
            "estimate": null,
            "estimate_forecast": null,
            "suite_id": 921,
            "display_order": 12,
            "is_deleted": 0,
            "case_assignedto_id": null,
            "custom_automation_type": 0,
            "custom_automatable": 1,
            "custom_automated": 1,
            "custom_deprecatedtestcase": null,
            "custom_ui_case": 1,
            "custom_automation_id": null,
            "custom_hack_functional_sub_categories": 1,
            "custom_hack_test_categories": 3,
            "custom_hack_jira_escalated": null,
            "custom_appliance_support": 2,
            "custom_sub_component": 48,
            "custom_testrail_bdd_scenario": null,
            "custom_summary": null,
            "custom_preconds": null,
            "custom_steps": "- Create DEIP policy with Source AND Destination\r\nSrc: User: bkodirangaiah@netskope.com\r\nDst: Domain==config.me\r\negress_ip_profile: \r\n      egress_ip_type:Dedicated/Shared\r\n      footprint : 12345\r\n- Vpop is disabled\r\n- Send traffic to not match the policy\r\n- Check that the policy is not matched, and ensure that the corresponding IPs are not used",
            "custom_expected": "- DEIP policy is not matched\r\n- DE/VPOP IP is not used for traffic\r\n- Review appmodule 3 logs to see so_mark not picked \r\n- Review policy 1 logs, to see EgressIP policy not being picked",
            "custom_steps_separated": null,
            "custom_mission": null,
            "custom_goals": null,
            "comments": [],
            "custom_keyword": [],
            "custom_stack_label": []
        },
        {
            "id": 1806467,
            "title": "Verify sending traffic to match 2 DEIP policy with different app and footprint",
            "section_id": 125298,
            "template_id": 1,
            "type_id": 6,
            "priority_id": 2,
            "milestone_id": null,
            "refs": "ENG-400726",
            "created_by": 398,
            "created_on": 1709679677,
            "updated_by": 729,
            "updated_on": 1736856007,
            "estimate": null,
            "estimate_forecast": null,
            "suite_id": 921,
            "display_order": 13,
            "is_deleted": 0,
            "case_assignedto_id": null,
            "custom_automation_type": 0,
            "custom_automatable": 1,
            "custom_automated": 1,
            "custom_deprecatedtestcase": false,
            "custom_ui_case": 1,
            "custom_automation_id": null,
            "custom_hack_functional_sub_categories": 1,
            "custom_hack_test_categories": 3,
            "custom_hack_jira_escalated": false,
            "custom_appliance_support": 2,
            "custom_sub_component": 48,
            "custom_testrail_bdd_scenario": null,
            "custom_summary": null,
            "custom_preconds": null,
            "custom_steps": "- Create tenant_footprint.json with two footprint both enabled\n- Create DEIP policy with \n   User:testuser-2@netskope.com\n   App:Office\n   \"egress_ip_type\": dedicated, footprint-1\n- Create DEIP policy with \n   User:testuser-2@netskope.com\n   App:Box\n   \"egress_ip_type\": dedicated, footprint-2\n- Send traffic to match both DEIP policy\n- Check that the corresponding IPs are used while sending traffic",
            "custom_expected": "- DEIP policy is matched\n- DEIP is used for traffic\n- Review appmodule 3 logs to see so_mark picked \n- Review policy 1 logs, to see EgressIP policy being picked indicated by ns_policy_apply_egress_ip_policy()",
            "custom_steps_separated": null,
            "custom_mission": null,
            "custom_goals": null,
            "comments": [],
            "custom_keyword": [],
            "custom_stack_label": []
        },
        {
            "id": 1806468,
            "title": "Verify sending traffic to match 2 DEIP policy with different user group and footprint",
            "section_id": 125298,
            "template_id": 1,
            "type_id": 6,
            "priority_id": 2,
            "milestone_id": null,
            "refs": "ENG-400726",
            "created_by": 398,
            "created_on": 1709679677,
            "updated_by": 729,
            "updated_on": 1736856007,
            "estimate": null,
            "estimate_forecast": null,
            "suite_id": 921,
            "display_order": 14,
            "is_deleted": 0,
            "case_assignedto_id": null,
            "custom_automation_type": 0,
            "custom_automatable": 1,
            "custom_automated": 1,
            "custom_deprecatedtestcase": false,
            "custom_ui_case": 1,
            "custom_automation_id": null,
            "custom_hack_functional_sub_categories": 1,
            "custom_hack_test_categories": 3,
            "custom_hack_jira_escalated": false,
            "custom_appliance_support": 2,
            "custom_sub_component": 48,
            "custom_testrail_bdd_scenario": null,
            "custom_summary": null,
            "custom_preconds": null,
            "custom_steps": "- Create tenant_footprint.json with two footprint both enabled\r\n- Create DEIP policy with \r\n   UserGroup:test-group1\r\n   App:Office\r\n   \"egress_ip_type\": dedicated, footprint-1\r\n- Create DEIP policy with \r\n   UserGroup:test-group2\r\n   App:Box\r\n   \"egress_ip_type\": dedicated, footprint-2\r\n- Send traffic to match both DEIP policy\r\n- Check that the corresponding IPs are used while sending traffic",
            "custom_expected": "- DEIP policy is matched\r\n- DEIP is used for traffic\r\n- Review appmodule 3 logs to see so_mark picked \r\n- Review policy 1 logs, to see EgressIP policy being picked indicated by ns_policy_apply_egress_ip_policy()",
            "custom_steps_separated": null,
            "custom_mission": null,
            "custom_goals": null,
            "comments": [],
            "custom_keyword": [],
            "custom_stack_label": []
        }
    ]
}