{
    "updated_cases": [
        {
            "id": 1536213,
            "title": "Verify whether we are able to apply altos universal connector  policy for  the custom categories",
            "section_id": 105452,
            "template_id": 1,
            "type_id": 6,
            "priority_id": 2,
            "milestone_id": null,
            "refs": null,
            "created_by": 350,
            "created_on": 1682328786,
            "updated_by": 729,
            "updated_on": 1736856089,
            "estimate": null,
            "estimate_forecast": null,
            "suite_id": 921,
            "display_order": 3,
            "is_deleted": 0,
            "case_assignedto_id": null,
            "custom_automation_type": 0,
            "custom_automatable": 1,
            "custom_automated": 1,
            "custom_deprecatedtestcase": null,
            "custom_ui_case": 1,
            "custom_automation_id": null,
            "custom_hack_functional_sub_categories": 1,
            "custom_hack_test_categories": 3,
            "custom_hack_jira_escalated": null,
            "custom_appliance_support": null,
            "custom_sub_component": 48,
            "custom_testrail_bdd_scenario": null,
            "custom_summary": "Verify whether we are able to apply altos universal connector  policy for  the custom categories",
            "custom_preconds": "Stack Should Be up and running and WebInfo build should be deployed",
            "custom_steps": "1",
            "custom_expected": "1. We should be able to Apply the policy for Custom Categories",
            "custom_steps_separated": null,
            "custom_mission": null,
            "custom_goals": null,
            "comments": [],
            "custom_keyword": [],
            "custom_stack_label": [
                4
            ]
        },
        {
            "id": 1536214,
            "title": "Verify Upload activity Block & Alert Altos web category Based Connector",
            "section_id": 105452,
            "template_id": 1,
            "type_id": 6,
            "priority_id": 2,
            "milestone_id": null,
            "refs": null,
            "created_by": 350,
            "created_on": 1682328786,
            "updated_by": 729,
            "updated_on": 1736856089,
            "estimate": null,
            "estimate_forecast": null,
            "suite_id": 921,
            "display_order": 4,
            "is_deleted": 0,
            "case_assignedto_id": null,
            "custom_automation_type": 0,
            "custom_automatable": 1,
            "custom_automated": 1,
            "custom_deprecatedtestcase": null,
            "custom_ui_case": 1,
            "custom_automation_id": null,
            "custom_hack_functional_sub_categories": 1,
            "custom_hack_test_categories": 3,
            "custom_hack_jira_escalated": null,
            "custom_appliance_support": null,
            "custom_sub_component": 48,
            "custom_testrail_bdd_scenario": null,
            "custom_summary": "Verify Upload activity Block & Alert Altos web category Based Connector",
            "custom_preconds": "Stack Should Be up and running and WebInfo build should be deployed",
            "custom_steps": "1",
            "custom_expected": "1. We should be able to Apply the policy for web categories",
            "custom_steps_separated": null,
            "custom_mission": null,
            "custom_goals": null,
            "comments": [],
            "custom_keyword": [],
            "custom_stack_label": [
                4
            ]
        },
        {
            "id": 1536215,
            "title": "Verify Upload DLP block & Alert for altos WEB category based connector",
            "section_id": 105452,
            "template_id": 1,
            "type_id": 6,
            "priority_id": 2,
            "milestone_id": null,
            "refs": null,
            "created_by": 350,
            "created_on": 1682328786,
            "updated_by": 729,
            "updated_on": 1736856089,
            "estimate": null,
            "estimate_forecast": null,
            "suite_id": 921,
            "display_order": 5,
            "is_deleted": 0,
            "case_assignedto_id": null,
            "custom_automation_type": 0,
            "custom_automatable": 1,
            "custom_automated": 1,
            "custom_deprecatedtestcase": null,
            "custom_ui_case": 1,
            "custom_automation_id": null,
            "custom_hack_functional_sub_categories": 1,
            "custom_hack_test_categories": 3,
            "custom_hack_jira_escalated": null,
            "custom_appliance_support": null,
            "custom_sub_component": 48,
            "custom_testrail_bdd_scenario": null,
            "custom_summary": "Verify Upload DLP block & Alert for altos WEB category based connector",
            "custom_preconds": "Stack Should Be up and running and WebInfo build should be deployed",
            "custom_steps": "1",
            "custom_expected": "1. We should be able to Apply the policy for web categories",
            "custom_steps_separated": null,
            "custom_mission": null,
            "custom_goals": null,
            "comments": [],
            "custom_keyword": [],
            "custom_stack_label": [
                4
            ]
        },
        {
            "id": 1536216,
            "title": "Verify Download Block & Alert  altos category based connector",
            "section_id": 105452,
            "template_id": 1,
            "type_id": 6,
            "priority_id": 2,
            "milestone_id": null,
            "refs": null,
            "created_by": 350,
            "created_on": 1682328786,
            "updated_by": 729,
            "updated_on": 1736856089,
            "estimate": null,
            "estimate_forecast": null,
            "suite_id": 921,
            "display_order": 6,
            "is_deleted": 0,
            "case_assignedto_id": null,
            "custom_automation_type": 0,
            "custom_automatable": 1,
            "custom_automated": 1,
            "custom_deprecatedtestcase": null,
            "custom_ui_case": 1,
            "custom_automation_id": null,
            "custom_hack_functional_sub_categories": 1,
            "custom_hack_test_categories": 3,
            "custom_hack_jira_escalated": null,
            "custom_appliance_support": null,
            "custom_sub_component": 48,
            "custom_testrail_bdd_scenario": null,
            "custom_summary": "Verify Download Block & Alert  altos category based connector",
            "custom_preconds": "Stack Should Be up and running and WebInfo build should be deployed",
            "custom_steps": "1",
            "custom_expected": "1. We should be able to Apply the policy for web categories",
            "custom_steps_separated": null,
            "custom_mission": null,
            "custom_goals": null,
            "comments": [],
            "custom_keyword": [],
            "custom_stack_label": [
                4
            ]
        },
        {
            "id": 1536217,
            "title": "Verify Download  DLP block & Alert Altos web category based connector",
            "section_id": 105452,
            "template_id": 1,
            "type_id": 6,
            "priority_id": 2,
            "milestone_id": null,
            "refs": null,
            "created_by": 350,
            "created_on": 1682328786,
            "updated_by": 729,
            "updated_on": 1736856089,
            "estimate": null,
            "estimate_forecast": null,
            "suite_id": 921,
            "display_order": 7,
            "is_deleted": 0,
            "case_assignedto_id": null,
            "custom_automation_type": 0,
            "custom_automatable": 1,
            "custom_automated": 1,
            "custom_deprecatedtestcase": null,
            "custom_ui_case": 1,
            "custom_automation_id": null,
            "custom_hack_functional_sub_categories": 1,
            "custom_hack_test_categories": 3,
            "custom_hack_jira_escalated": null,
            "custom_appliance_support": null,
            "custom_sub_component": 48,
            "custom_testrail_bdd_scenario": null,
            "custom_summary": "Verify Download  DLP block & Alert Altos web category based connector",
            "custom_preconds": "Stack Should Be up and running and WebInfo build should be deployed",
            "custom_steps": "1",
            "custom_expected": "1. Verify Download DLP block & Alert Altos web category based connector",
            "custom_steps_separated": null,
            "custom_mission": null,
            "custom_goals": null,
            "comments": [],
            "custom_keyword": [],
            "custom_stack_label": [
                4
            ]
        },
        {
            "id": 1536218,
            "title": "Verify POST  DLP block & Alert Altos category based connector",
            "section_id": 105452,
            "template_id": 1,
            "type_id": 6,
            "priority_id": 2,
            "milestone_id": null,
            "refs": null,
            "created_by": 350,
            "created_on": 1682328786,
            "updated_by": 729,
            "updated_on": 1736856089,
            "estimate": null,
            "estimate_forecast": null,
            "suite_id": 921,
            "display_order": 8,
            "is_deleted": 0,
            "case_assignedto_id": null,
            "custom_automation_type": 0,
            "custom_automatable": 1,
            "custom_automated": 1,
            "custom_deprecatedtestcase": null,
            "custom_ui_case": 1,
            "custom_automation_id": null,
            "custom_hack_functional_sub_categories": 1,
            "custom_hack_test_categories": 3,
            "custom_hack_jira_escalated": null,
            "custom_appliance_support": null,
            "custom_sub_component": 48,
            "custom_testrail_bdd_scenario": null,
            "custom_summary": "Verify POST  DLP block & Alert Altos category based connector",
            "custom_preconds": "Stack Should Be up and running and WebInfo build should be deployed",
            "custom_steps": "1",
            "custom_expected": "1. We should be able to Apply the policy for web categories",
            "custom_steps_separated": null,
            "custom_mission": null,
            "custom_goals": null,
            "comments": [],
            "custom_keyword": [],
            "custom_stack_label": [
                4
            ]
        },
        {
            "id": 1536219,
            "title": "Verify POST   block & Alert Altos category based connector",
            "section_id": 105452,
            "template_id": 1,
            "type_id": 6,
            "priority_id": 2,
            "milestone_id": null,
            "refs": null,
            "created_by": 350,
            "created_on": 1682328786,
            "updated_by": 729,
            "updated_on": 1736856089,
            "estimate": null,
            "estimate_forecast": null,
            "suite_id": 921,
            "display_order": 9,
            "is_deleted": 0,
            "case_assignedto_id": null,
            "custom_automation_type": 0,
            "custom_automatable": 1,
            "custom_automated": 1,
            "custom_deprecatedtestcase": null,
            "custom_ui_case": 1,
            "custom_automation_id": null,
            "custom_hack_functional_sub_categories": 1,
            "custom_hack_test_categories": 3,
            "custom_hack_jira_escalated": null,
            "custom_appliance_support": null,
            "custom_sub_component": 48,
            "custom_testrail_bdd_scenario": null,
            "custom_summary": "Verify POST   block & Alert Altos category based connector",
            "custom_preconds": "Stack Should Be up and running and WebInfo build should be deployed",
            "custom_steps": "1",
            "custom_expected": "1. We should be able to Apply the policy for web categories",
            "custom_steps_separated": null,
            "custom_mission": null,
            "custom_goals": null,
            "comments": [],
            "custom_keyword": [],
            "custom_stack_label": [
                4
            ]
        },
        {
            "id": 1536220,
            "title": "Verify whether traffic is hitting to the \"altos_universal_connector\" when there is no altos_category_based_connector\" present",
            "section_id": 105452,
            "template_id": 1,
            "type_id": 6,
            "priority_id": 2,
            "milestone_id": null,
            "refs": null,
            "created_by": 350,
            "created_on": 1682328786,
            "updated_by": 729,
            "updated_on": 1736856089,
            "estimate": null,
            "estimate_forecast": null,
            "suite_id": 921,
            "display_order": 10,
            "is_deleted": 0,
            "case_assignedto_id": null,
            "custom_automation_type": 0,
            "custom_automatable": 1,
            "custom_automated": 1,
            "custom_deprecatedtestcase": null,
            "custom_ui_case": 1,
            "custom_automation_id": null,
            "custom_hack_functional_sub_categories": 1,
            "custom_hack_test_categories": 3,
            "custom_hack_jira_escalated": null,
            "custom_appliance_support": null,
            "custom_sub_component": 48,
            "custom_testrail_bdd_scenario": null,
            "custom_summary": "Verify whether traffic is hitting to the \"altos_universal_connector\" when there is no altos_category_based_connector\" present",
            "custom_preconds": "Stack Should Be up and running and WebInfo build should be deployed",
            "custom_steps": "1",
            "custom_expected": "1. We should be able to Apply the policy for web based universal categories",
            "custom_steps_separated": null,
            "custom_mission": null,
            "custom_goals": null,
            "comments": [],
            "custom_keyword": [],
            "custom_stack_label": [
                4
            ]
        },
        {
            "id": 1536221,
            "title": "With the \"altos_universal_connector\" Alert Policy ,Verify by accessing different category websites",
            "section_id": 105452,
            "template_id": 1,
            "type_id": 6,
            "priority_id": 2,
            "milestone_id": null,
            "refs": null,
            "created_by": 350,
            "created_on": 1682328786,
            "updated_by": 729,
            "updated_on": 1736856089,
            "estimate": null,
            "estimate_forecast": null,
            "suite_id": 921,
            "display_order": 11,
            "is_deleted": 0,
            "case_assignedto_id": null,
            "custom_automation_type": 0,
            "custom_automatable": 1,
            "custom_automated": 1,
            "custom_deprecatedtestcase": null,
            "custom_ui_case": 1,
            "custom_automation_id": null,
            "custom_hack_functional_sub_categories": 1,
            "custom_hack_test_categories": 3,
            "custom_hack_jira_escalated": null,
            "custom_appliance_support": null,
            "custom_sub_component": 48,
            "custom_testrail_bdd_scenario": null,
            "custom_summary": "With the \"altos_universal_connector\" Alert Policy ,Verify by accessing different category websites",
            "custom_preconds": "Stack Should Be up and running and WebInfo build should be deployed",
            "custom_steps": "1",
            "custom_expected": "1. We should be able to Apply the policy for web based universal categories",
            "custom_steps_separated": null,
            "custom_mission": null,
            "custom_goals": null,
            "comments": [],
            "custom_keyword": [],
            "custom_stack_label": [
                4
            ]
        },
        {
            "id": 1536222,
            "title": "With the \"altos_universal_connector\" DLP POST Alert & Block Policy ,verify  the policy action",
            "section_id": 105452,
            "template_id": 1,
            "type_id": 6,
            "priority_id": 2,
            "milestone_id": null,
            "refs": null,
            "created_by": 350,
            "created_on": 1682328786,
            "updated_by": 729,
            "updated_on": 1736856089,
            "estimate": null,
            "estimate_forecast": null,
            "suite_id": 921,
            "display_order": 12,
            "is_deleted": 0,
            "case_assignedto_id": null,
            "custom_automation_type": 0,
            "custom_automatable": 1,
            "custom_automated": 1,
            "custom_deprecatedtestcase": null,
            "custom_ui_case": 1,
            "custom_automation_id": null,
            "custom_hack_functional_sub_categories": 1,
            "custom_hack_test_categories": 3,
            "custom_hack_jira_escalated": null,
            "custom_appliance_support": null,
            "custom_sub_component": 48,
            "custom_testrail_bdd_scenario": null,
            "custom_summary": "With the \"altos_universal_connector\" DLP POST Alert & Block Policy ,verify  the policy action",
            "custom_preconds": "Stack Should Be up and running and WebInfo build should be deployed",
            "custom_steps": "1",
            "custom_expected": "1. With the \"altos\\_universal\\_connector\" DLP POST Alert & Block Policy ,verify the policy action",
            "custom_steps_separated": null,
            "custom_mission": null,
            "custom_goals": null,
            "comments": [],
            "custom_keyword": [],
            "custom_stack_label": [
                4
            ]
        }
    ]
}