{
    "updated_cases": [
        {
            "id": 1779958,
            "title": "Verify that UCIDownloader handle failed to consume pub/sub notification",
            "section_id": 123350,
            "template_id": 1,
            "type_id": 6,
            "priority_id": 2,
            "milestone_id": null,
            "refs": null,
            "created_by": 675,
            "created_on": 1702380007,
            "updated_by": 729,
            "updated_on": 1736855919,
            "estimate": null,
            "estimate_forecast": null,
            "suite_id": 921,
            "display_order": 36,
            "is_deleted": 0,
            "case_assignedto_id": 675,
            "custom_automation_type": 0,
            "custom_automatable": 0,
            "custom_automated": 0,
            "custom_deprecatedtestcase": null,
            "custom_ui_case": 1,
            "custom_automation_id": null,
            "custom_hack_functional_sub_categories": 2,
            "custom_hack_test_categories": 3,
            "custom_hack_jira_escalated": null,
            "custom_appliance_support": 2,
            "custom_sub_component": 48,
            "custom_testrail_bdd_scenario": null,
            "custom_summary": "Verify that UCIDownloader handle failed to consume pub/sub notification",
            "custom_preconds": null,
            "custom_steps": null,
            "custom_expected": null,
            "custom_steps_separated": null,
            "custom_mission": null,
            "custom_goals": null,
            "comments": [],
            "custom_keyword": [],
            "custom_stack_label": []
        },
        {
            "id": 1779959,
            "title": "Verify UCIDownloader runs on FedRamp compliance node.",
            "section_id": 123350,
            "template_id": 1,
            "type_id": 16,
            "priority_id": 2,
            "milestone_id": null,
            "refs": null,
            "created_by": 675,
            "created_on": 1702380007,
            "updated_by": 729,
            "updated_on": 1736855919,
            "estimate": null,
            "estimate_forecast": null,
            "suite_id": 921,
            "display_order": 37,
            "is_deleted": 0,
            "case_assignedto_id": 675,
            "custom_automation_type": 0,
            "custom_automatable": 0,
            "custom_automated": 0,
            "custom_deprecatedtestcase": false,
            "custom_ui_case": 1,
            "custom_automation_id": null,
            "custom_hack_functional_sub_categories": 1,
            "custom_hack_test_categories": 3,
            "custom_hack_jira_escalated": false,
            "custom_appliance_support": 2,
            "custom_sub_component": 48,
            "custom_testrail_bdd_scenario": null,
            "custom_summary": "Verify UCIDownloader runs on FedRamp compliance node.",
            "custom_preconds": null,
            "custom_steps": "Deploy UCIDownloader on FedRamp dataplane node",
            "custom_expected": "- UCI score file update should have an interval of 10 mins.\n- UCIDownloader should subscripbe to only1 FedRamp topic",
            "custom_steps_separated": null,
            "custom_mission": null,
            "custom_goals": null,
            "comments": [],
            "custom_keyword": [],
            "custom_stack_label": []
        },
        {
            "id": 1779960,
            "title": "Verify UCIDownloader runs on PBMM compliance.",
            "section_id": 123350,
            "template_id": 1,
            "type_id": 16,
            "priority_id": 2,
            "milestone_id": null,
            "refs": null,
            "created_by": 675,
            "created_on": 1702380007,
            "updated_by": 729,
            "updated_on": 1736855919,
            "estimate": null,
            "estimate_forecast": null,
            "suite_id": 921,
            "display_order": 38,
            "is_deleted": 0,
            "case_assignedto_id": 675,
            "custom_automation_type": 0,
            "custom_automatable": 0,
            "custom_automated": 0,
            "custom_deprecatedtestcase": false,
            "custom_ui_case": 1,
            "custom_automation_id": null,
            "custom_hack_functional_sub_categories": 1,
            "custom_hack_test_categories": 3,
            "custom_hack_jira_escalated": false,
            "custom_appliance_support": 2,
            "custom_sub_component": 48,
            "custom_testrail_bdd_scenario": null,
            "custom_summary": "Verify UCIDownloader runs on PBMM compliance.",
            "custom_preconds": null,
            "custom_steps": "Deploy UCIDownloader on PBMM dataplane node",
            "custom_expected": "- UCI score file update should have an interval of 10 mins.\n- UCIDownloader should subscripbe to only1 PBMM topic",
            "custom_steps_separated": null,
            "custom_mission": null,
            "custom_goals": null,
            "comments": [],
            "custom_keyword": [],
            "custom_stack_label": []
        },
        {
            "id": 1779961,
            "title": "Verify UCIDownloader runs on China PoP compliance.",
            "section_id": 123350,
            "template_id": 1,
            "type_id": 16,
            "priority_id": 2,
            "milestone_id": null,
            "refs": null,
            "created_by": 675,
            "created_on": 1702380007,
            "updated_by": 729,
            "updated_on": 1736855919,
            "estimate": null,
            "estimate_forecast": null,
            "suite_id": 921,
            "display_order": 39,
            "is_deleted": 0,
            "case_assignedto_id": 675,
            "custom_automation_type": 0,
            "custom_automatable": 0,
            "custom_automated": 0,
            "custom_deprecatedtestcase": false,
            "custom_ui_case": 1,
            "custom_automation_id": null,
            "custom_hack_functional_sub_categories": 1,
            "custom_hack_test_categories": 3,
            "custom_hack_jira_escalated": false,
            "custom_appliance_support": 2,
            "custom_sub_component": 48,
            "custom_testrail_bdd_scenario": null,
            "custom_summary": "Verify UCIDownloader runs on China PoP compliance.",
            "custom_preconds": null,
            "custom_steps": "Deploy UCIDownloader on China PoP dataplane node",
            "custom_expected": "- UCI score file update should have an interval of 10 mins.\n- UCIDownloader should subscripbe to only1 China topic with 12 bucket notification.",
            "custom_steps_separated": null,
            "custom_mission": null,
            "custom_goals": null,
            "comments": [],
            "custom_keyword": [],
            "custom_stack_label": []
        },
        {
            "id": 1779962,
            "title": "Verify that an alert is triggered when a user's UCI score falls below a specified threshold.",
            "section_id": 123350,
            "template_id": 1,
            "type_id": 6,
            "priority_id": 2,
            "milestone_id": null,
            "refs": null,
            "created_by": 675,
            "created_on": 1702380007,
            "updated_by": 729,
            "updated_on": 1736855919,
            "estimate": null,
            "estimate_forecast": null,
            "suite_id": 921,
            "display_order": 40,
            "is_deleted": 0,
            "case_assignedto_id": 675,
            "custom_automation_type": 0,
            "custom_automatable": 1,
            "custom_automated": 1,
            "custom_deprecatedtestcase": null,
            "custom_ui_case": 1,
            "custom_automation_id": null,
            "custom_hack_functional_sub_categories": 1,
            "custom_hack_test_categories": 3,
            "custom_hack_jira_escalated": null,
            "custom_appliance_support": 2,
            "custom_sub_component": 48,
            "custom_testrail_bdd_scenario": null,
            "custom_summary": "Verify that an alert is triggered when a user's UCI score falls below a specified threshold.",
            "custom_preconds": "An alert policy is set up with UCI score below 500.\r\nA user has score above 500.",
            "custom_steps": "- Update UCI score of the user below 500 in a per 10 mins frequency.\r\n- Check if an alert is generated.",
            "custom_expected": "An alert should be generated when the UCI score falls below 500",
            "custom_steps_separated": null,
            "custom_mission": null,
            "custom_goals": null,
            "comments": [],
            "custom_keyword": [],
            "custom_stack_label": []
        },
        {
            "id": 1779963,
            "title": "Verify that users with UCI scores above a certain threshold is allow access specified web applications.",
            "section_id": 123350,
            "template_id": 1,
            "type_id": 6,
            "priority_id": 2,
            "milestone_id": null,
            "refs": null,
            "created_by": 675,
            "created_on": 1702380007,
            "updated_by": 729,
            "updated_on": 1736855919,
            "estimate": null,
            "estimate_forecast": null,
            "suite_id": 921,
            "display_order": 41,
            "is_deleted": 0,
            "case_assignedto_id": 675,
            "custom_automation_type": 0,
            "custom_automatable": 1,
            "custom_automated": 1,
            "custom_deprecatedtestcase": null,
            "custom_ui_case": 1,
            "custom_automation_id": null,
            "custom_hack_functional_sub_categories": 1,
            "custom_hack_test_categories": 3,
            "custom_hack_jira_escalated": null,
            "custom_appliance_support": 2,
            "custom_sub_component": 48,
            "custom_testrail_bdd_scenario": null,
            "custom_summary": "Verify that users with UCI scores above a certain threshold is allow access specified web applications.",
            "custom_preconds": "An allow policy is set up with UCI score above 501.\r\nA user has score below 501.",
            "custom_steps": "- Update UCI score of the user above 501 in a per 10 mins frequency.\r\n- Attempt to access a web application.",
            "custom_expected": "Access to the web application should be allowed for users with UCI scores above the 501.",
            "custom_steps_separated": null,
            "custom_mission": null,
            "custom_goals": null,
            "comments": [],
            "custom_keyword": [],
            "custom_stack_label": []
        },
        {
            "id": 1779964,
            "title": "Verify that access to certain web categories is blocked for users with UCI scores below a certain threshold.",
            "section_id": 123350,
            "template_id": 1,
            "type_id": 6,
            "priority_id": 2,
            "milestone_id": null,
            "refs": null,
            "created_by": 675,
            "created_on": 1702380007,
            "updated_by": 729,
            "updated_on": 1736855919,
            "estimate": null,
            "estimate_forecast": null,
            "suite_id": 921,
            "display_order": 42,
            "is_deleted": 0,
            "case_assignedto_id": 675,
            "custom_automation_type": 0,
            "custom_automatable": 1,
            "custom_automated": 1,
            "custom_deprecatedtestcase": null,
            "custom_ui_case": 1,
            "custom_automation_id": null,
            "custom_hack_functional_sub_categories": 1,
            "custom_hack_test_categories": 3,
            "custom_hack_jira_escalated": null,
            "custom_appliance_support": 2,
            "custom_sub_component": 48,
            "custom_testrail_bdd_scenario": null,
            "custom_summary": "Verify that access to certain web categories is blocked for users with UCI scores below a certain threshold.",
            "custom_preconds": "A block policy is set up with UCI score below 300.\r\nA user has score below 300.",
            "custom_steps": "- Update UCI score of the user below 300 in a per 10 mins frequency.\r\n- Attempt to access the restricted web category.",
            "custom_expected": "Access to the specified web category should be blocked for users with UCI scores below the 300.",
            "custom_steps_separated": null,
            "custom_mission": null,
            "custom_goals": null,
            "comments": [],
            "custom_keyword": [],
            "custom_stack_label": []
        },
        {
            "id": 1779965,
            "title": "Verify the combination of alert and block policies for a web application based on UCI score changed.",
            "section_id": 123350,
            "template_id": 1,
            "type_id": 6,
            "priority_id": 2,
            "milestone_id": null,
            "refs": null,
            "created_by": 675,
            "created_on": 1702380007,
            "updated_by": 729,
            "updated_on": 1736855919,
            "estimate": null,
            "estimate_forecast": null,
            "suite_id": 921,
            "display_order": 43,
            "is_deleted": 0,
            "case_assignedto_id": 675,
            "custom_automation_type": 0,
            "custom_automatable": 0,
            "custom_automated": 0,
            "custom_deprecatedtestcase": null,
            "custom_ui_case": 1,
            "custom_automation_id": null,
            "custom_hack_functional_sub_categories": 1,
            "custom_hack_test_categories": 3,
            "custom_hack_jira_escalated": null,
            "custom_appliance_support": 2,
            "custom_sub_component": 48,
            "custom_testrail_bdd_scenario": null,
            "custom_summary": "Verify the combination of alert and block policies for a web application based on UCI score changed.",
            "custom_preconds": "An alert policy and an block are set up with UCI score below 500",
            "custom_steps": "- Update UCI score of the user above 500 in a per 10 mins frequency.\r\n- Attempt to access the web application and monitor alerts.",
            "custom_expected": "A alerts should be generated and NSProxy should block access when UCI score is below 500.",
            "custom_steps_separated": null,
            "custom_mission": null,
            "custom_goals": null,
            "comments": [],
            "custom_keyword": [],
            "custom_stack_label": []
        },
        {
            "id": 1779966,
            "title": "Verify that policies are applied across multiple users with similar UCI scores.",
            "section_id": 123350,
            "template_id": 1,
            "type_id": 6,
            "priority_id": 2,
            "milestone_id": null,
            "refs": null,
            "created_by": 675,
            "created_on": 1702380008,
            "updated_by": 729,
            "updated_on": 1736855919,
            "estimate": null,
            "estimate_forecast": null,
            "suite_id": 921,
            "display_order": 44,
            "is_deleted": 0,
            "case_assignedto_id": 675,
            "custom_automation_type": 0,
            "custom_automatable": 0,
            "custom_automated": 0,
            "custom_deprecatedtestcase": false,
            "custom_ui_case": 1,
            "custom_automation_id": null,
            "custom_hack_functional_sub_categories": 1,
            "custom_hack_test_categories": 3,
            "custom_hack_jira_escalated": false,
            "custom_appliance_support": 2,
            "custom_sub_component": 48,
            "custom_testrail_bdd_scenario": null,
            "custom_summary": "Verify that policies are applied across multiple users with similar UCI scores.",
            "custom_preconds": "A block policy is set up with UCI score below 300 on multiple user",
            "custom_steps": "- Update UCI score of multiple users below 500 in a per 10 mins frequency.\n- Verify if the policy is applied across these users.",
            "custom_expected": "All users with similar UCI scores should experience consistent policy.",
            "custom_steps_separated": null,
            "custom_mission": null,
            "custom_goals": null,
            "comments": [],
            "custom_keyword": [],
            "custom_stack_label": []
        },
        {
            "id": 1779967,
            "title": "Verify UCIDownloader handle both China DP tenant and Commercial tenant in the same time",
            "section_id": 123350,
            "template_id": 1,
            "type_id": 6,
            "priority_id": 2,
            "milestone_id": null,
            "refs": null,
            "created_by": 675,
            "created_on": 1702380008,
            "updated_by": 729,
            "updated_on": 1736855919,
            "estimate": null,
            "estimate_forecast": null,
            "suite_id": 921,
            "display_order": 45,
            "is_deleted": 0,
            "case_assignedto_id": 675,
            "custom_automation_type": 0,
            "custom_automatable": 0,
            "custom_automated": 0,
            "custom_deprecatedtestcase": true,
            "custom_ui_case": 1,
            "custom_automation_id": null,
            "custom_hack_functional_sub_categories": 1,
            "custom_hack_test_categories": 3,
            "custom_hack_jira_escalated": false,
            "custom_appliance_support": 2,
            "custom_sub_component": 48,
            "custom_testrail_bdd_scenario": null,
            "custom_summary": "Verify UCIDownloader handle both China DP tenant and Commercial tenant in the same time",
            "custom_preconds": "- 1 NSProxy UCIDownloader subscribes to the commercial UCI notification topic\r\n- 1 NSProxy UCIDownloader subscribes to the China UCI notification topic.",
            "custom_steps": "- Update UCI score of China DP tenant\r\n- Update UCI score of commertial tenant\r\n- Check UCIDownloader download the correct files that accordingly\r\n- Monitor UCIDownloader logs",
            "custom_expected": "- UCIDownloader should download the correct UCI score files.",
            "custom_steps_separated": null,
            "custom_mission": null,
            "custom_goals": null,
            "comments": [],
            "custom_keyword": [],
            "custom_stack_label": []
        }
    ]
}